wheel_metadata_injector-0.0.6.dist-info/METADATA
wheel_metadata_injector-0.0.6.dist-info/WHEEL
wheel_metadata_injector-0.0.6.dist-info/entry_points.txt
wheel_metadata_injector.libs/libcom_err-2abe824b.so.2
wheel_metadata_injector.libs/libcrypto-d3570994.so.10
wheel_metadata_injector.libs/libgssapi_krb5-497db0c6.so.2
wheel_metadata_injector.libs/libk5crypto-b1f99d5c.so.3
wheel_metadata_injector.libs/libkeyutils-dfe70bd6.so.1
wheel_metadata_injector.libs/libkrb5-fcafa220.so.3
wheel_metadata_injector.libs/libkrb5support-d0bcff84.so.0
wheel_metadata_injector.libs/libpcre-9513aab5.so.1
wheel_metadata_injector.libs/libselinux-0922c95c.so.1
wheel_metadata_injector.libs/libssl-cd1d6220.so.10
wheel_metadata_injector/cli.py
wheel_metadata_injector/setuptools_plugin.py
wheel_metadata_injector/__init__.py
wheel_metadata_injector/_wheel_metadata_injector.abi3.so
wheel_metadata_injector-0.0.6.dist-info/RECORD
