Metadata-Version: 2.4
Name: wheel-metadata-injector
Version: 0.0.6
Classifier: Programming Language :: Rust
Classifier: Programming Language :: Python :: Implementation :: CPython
Classifier: Programming Language :: Python :: 3.8
Classifier: Programming Language :: Python :: 3.9
Classifier: Programming Language :: Python :: 3.10
Classifier: Programming Language :: Python :: 3.11
Classifier: Programming Language :: Python :: 3.12
Classifier: Framework :: Setuptools Plugin
Requires-Dist: setuptools>=42.0.0
Requires-Dist: wheel>=0.37.0
Requires-Python: >=3.8
